PyNutil/__init__.py
PyNutil/config.py
PyNutil/main.py
PyNutil/io/__init__.py
PyNutil/io/atlas_loader.py
PyNutil/io/file_operations.py
PyNutil/io/nifti_writer.py
PyNutil/io/propagation.py
PyNutil/io/read_and_write.py
PyNutil/io/reconstruct_dzi.py
PyNutil/io/section_visualisation.py
PyNutil/io/volume_nifti.py
PyNutil/processing/__init__.py
PyNutil/processing/aggregator.py
PyNutil/processing/coordinate_extraction.py
PyNutil/processing/counting_and_load.py
PyNutil/processing/data_analysis.py
PyNutil/processing/generate_target_slice.py
PyNutil/processing/image_loaders.py
PyNutil/processing/section_volume.py
PyNutil/processing/transform.py
PyNutil/processing/transformations.py
PyNutil/processing/utils.py
PyNutil/processing/visualign_deformations.py
pynutil-0.3.3.dist-info/licenses/LICENSE
pynutil-0.3.3.dist-info/METADATA
pynutil-0.3.3.dist-info/WHEEL
pynutil-0.3.3.dist-info/top_level.txt
pynutil-0.3.3.dist-info/RECORD
