Metadata-Version: 2.4
Name: PyNutil
Version: 0.3.3
Summary: a package to quantify atlas registered brain data
Home-page: https://github.com/Neural-Systems-at-UIO/PyNutil
License: MIT
License-File: LICENSE
Requires-Dist: numpy
Requires-Dist: brainglobe-atlasapi
Requires-Dist: pandas
Requires-Dist: pynrrd
Requires-Dist: xmltodict
Requires-Dist: opencv-python
Requires-Dist: scipy
Requires-Dist: nibabel
Dynamic: description
Dynamic: description-content-type
Dynamic: home-page
Dynamic: license
Dynamic: license-file
Dynamic: requires-dist
Dynamic: summary
